[{"ANIO":2020,"TIPO_ACCIDENTE_NOMBRE":1.0,"TOTAL":35},{"ANIO":2020,"TIPO_ACCIDENTE_NOMBRE":2.0,"TOTAL":49},{"ANIO":2020,"TIPO_ACCIDENTE_NOMBRE":3.0,"TOTAL":15},{"ANIO":2020,"TIPO_ACCIDENTE_NOMBRE":4.0,"TOTAL":20},{"ANIO":2020,"TIPO_ACCIDENTE_NOMBRE":5.0,"TOTAL":3},{"ANIO":2020,"TIPO_ACCIDENTE_NOMBRE":6.0,"TOTAL":19},{"ANIO":2020,"TIPO_ACCIDENTE_NOMBRE":7.0,"TOTAL":2},{"ANIO":2020,"TIPO_ACCIDENTE_NOMBRE":9.0,"TOTAL":9},{"ANIO":2020,"TIPO_ACCIDENTE_NOMBRE":10.0,"TOTAL":14},{"ANIO":2020,"TIPO_ACCIDENTE_NOMBRE":12.0,"TOTAL":25},{"ANIO":2020,"TIPO_ACCIDENTE_NOMBRE":13.0,"TOTAL":3},{"ANIO":2020,"TIPO_ACCIDENTE_NOMBRE":14.0,"TOTAL":3},{"ANIO":2020,"TIPO_ACCIDENTE_NOMBRE":15.0,"TOTAL":10},{"ANIO":2020,"TIPO_ACCIDENTE_NOMBRE":16.0,"TOTAL":52},{"ANIO":2020,"TIPO_ACCIDENTE_NOMBRE":17.0,"TOTAL":3},{"ANIO":2020,"TIPO_ACCIDENTE_NOMBRE":18.0,"TOTAL":5},{"ANIO":2020,"TIPO_ACCIDENTE_NOMBRE":19.0,"TOTAL":27},{"ANIO":2020,"TIPO_ACCIDENTE_NOMBRE":20.0,"TOTAL":7},{"ANIO":2021,"TIPO_ACCIDENTE_NOMBRE":1.0,"TOTAL":32},{"ANIO":2021,"TIPO_ACCIDENTE_NOMBRE":2.0,"TOTAL":61},{"ANIO":2021,"TIPO_ACCIDENTE_NOMBRE":3.0,"TOTAL":21},{"ANIO":2021,"TIPO_ACCIDENTE_NOMBRE":4.0,"TOTAL":23},{"ANIO":2021,"TIPO_ACCIDENTE_NOMBRE":5.0,"TOTAL":1},{"ANIO":2021,"TIPO_ACCIDENTE_NOMBRE":6.0,"TOTAL":16},{"ANIO":2021,"TIPO_ACCIDENTE_NOMBRE":7.0,"TOTAL":3},{"ANIO":2021,"TIPO_ACCIDENTE_NOMBRE":8.0,"TOTAL":3},{"ANIO":2021,"TIPO_ACCIDENTE_NOMBRE":9.0,"TOTAL":13},{"ANIO":2021,"TIPO_ACCIDENTE_NOMBRE":10.0,"TOTAL":14},{"ANIO":2021,"TIPO_ACCIDENTE_NOMBRE":12.0,"TOTAL":36},{"ANIO":2021,"TIPO_ACCIDENTE_NOMBRE":13.0,"TOTAL":2},{"ANIO":2021,"TIPO_ACCIDENTE_NOMBRE":14.0,"TOTAL":2},{"ANIO":2021,"TIPO_ACCIDENTE_NOMBRE":15.0,"TOTAL":27},{"ANIO":2021,"TIPO_ACCIDENTE_NOMBRE":16.0,"TOTAL":42},{"ANIO":2021,"TIPO_ACCIDENTE_NOMBRE":17.0,"TOTAL":1},{"ANIO":2021,"TIPO_ACCIDENTE_NOMBRE":18.0,"TOTAL":7},{"ANIO":2021,"TIPO_ACCIDENTE_NOMBRE":19.0,"TOTAL":30},{"ANIO":2021,"TIPO_ACCIDENTE_NOMBRE":20.0,"TOTAL":12},{"ANIO":2022,"TIPO_ACCIDENTE_NOMBRE":1.0,"TOTAL":40},{"ANIO":2022,"TIPO_ACCIDENTE_NOMBRE":2.0,"TOTAL":55},{"ANIO":2022,"TIPO_ACCIDENTE_NOMBRE":3.0,"TOTAL":25},{"ANIO":2022,"TIPO_ACCIDENTE_NOMBRE":4.0,"TOTAL":28},{"ANIO":2022,"TIPO_ACCIDENTE_NOMBRE":6.0,"TOTAL":16},{"ANIO":2022,"TIPO_ACCIDENTE_NOMBRE":7.0,"TOTAL":2},{"ANIO":2022,"TIPO_ACCIDENTE_NOMBRE":9.0,"TOTAL":10},{"ANIO":2022,"TIPO_ACCIDENTE_NOMBRE":10.0,"TOTAL":13},{"ANIO":2022,"TIPO_ACCIDENTE_NOMBRE":12.0,"TOTAL":39},{"ANIO":2022,"TIPO_ACCIDENTE_NOMBRE":13.0,"TOTAL":4},{"ANIO":2022,"TIPO_ACCIDENTE_NOMBRE":14.0,"TOTAL":2},{"ANIO":2022,"TIPO_ACCIDENTE_NOMBRE":15.0,"TOTAL":16},{"ANIO":2022,"TIPO_ACCIDENTE_NOMBRE":16.0,"TOTAL":59},{"ANIO":2022,"TIPO_ACCIDENTE_NOMBRE":17.0,"TOTAL":5},{"ANIO":2022,"TIPO_ACCIDENTE_NOMBRE":18.0,"TOTAL":6},{"ANIO":2022,"TIPO_ACCIDENTE_NOMBRE":19.0,"TOTAL":39},{"ANIO":2022,"TIPO_ACCIDENTE_NOMBRE":20.0,"TOTAL":10},{"ANIO":2023,"TIPO_ACCIDENTE_NOMBRE":1.0,"TOTAL":46},{"ANIO":2023,"TIPO_ACCIDENTE_NOMBRE":2.0,"TOTAL":68},{"ANIO":2023,"TIPO_ACCIDENTE_NOMBRE":3.0,"TOTAL":25},{"ANIO":2023,"TIPO_ACCIDENTE_NOMBRE":4.0,"TOTAL":40},{"ANIO":2023,"TIPO_ACCIDENTE_NOMBRE":5.0,"TOTAL":2},{"ANIO":2023,"TIPO_ACCIDENTE_NOMBRE":6.0,"TOTAL":11},{"ANIO":2023,"TIPO_ACCIDENTE_NOMBRE":7.0,"TOTAL":4},{"ANIO":2023,"TIPO_ACCIDENTE_NOMBRE":8.0,"TOTAL":4},{"ANIO":2023,"TIPO_ACCIDENTE_NOMBRE":9.0,"TOTAL":11},{"ANIO":2023,"TIPO_ACCIDENTE_NOMBRE":10.0,"TOTAL":23},{"ANIO":2023,"TIPO_ACCIDENTE_NOMBRE":11.0,"TOTAL":1},{"ANIO":2023,"TIPO_ACCIDENTE_NOMBRE":12.0,"TOTAL":40},{"ANIO":2023,"TIPO_ACCIDENTE_NOMBRE":13.0,"TOTAL":4},{"ANIO":2023,"TIPO_ACCIDENTE_NOMBRE":14.0,"TOTAL":2},{"ANIO":2023,"TIPO_ACCIDENTE_NOMBRE":15.0,"TOTAL":22},{"ANIO":2023,"TIPO_ACCIDENTE_NOMBRE":16.0,"TOTAL":56},{"ANIO":2023,"TIPO_ACCIDENTE_NOMBRE":17.0,"TOTAL":1},{"ANIO":2023,"TIPO_ACCIDENTE_NOMBRE":18.0,"TOTAL":9},{"ANIO":2023,"TIPO_ACCIDENTE_NOMBRE":19.0,"TOTAL":41},{"ANIO":2023,"TIPO_ACCIDENTE_NOMBRE":20.0,"TOTAL":12},{"ANIO":2024,"TIPO_ACCIDENTE_NOMBRE":1.0,"TOTAL":46},{"ANIO":2024,"TIPO_ACCIDENTE_NOMBRE":2.0,"TOTAL":55},{"ANIO":2024,"TIPO_ACCIDENTE_NOMBRE":3.0,"TOTAL":30},{"ANIO":2024,"TIPO_ACCIDENTE_NOMBRE":4.0,"TOTAL":44},{"ANIO":2024,"TIPO_ACCIDENTE_NOMBRE":5.0,"TOTAL":2},{"ANIO":2024,"TIPO_ACCIDENTE_NOMBRE":6.0,"TOTAL":11},{"ANIO":2024,"TIPO_ACCIDENTE_NOMBRE":7.0,"TOTAL":5},{"ANIO":2024,"TIPO_ACCIDENTE_NOMBRE":8.0,"TOTAL":3},{"ANIO":2024,"TIPO_ACCIDENTE_NOMBRE":9.0,"TOTAL":11},{"ANIO":2024,"TIPO_ACCIDENTE_NOMBRE":10.0,"TOTAL":19},{"ANIO":2024,"TIPO_ACCIDENTE_NOMBRE":12.0,"TOTAL":48},{"ANIO":2024,"TIPO_ACCIDENTE_NOMBRE":13.0,"TOTAL":4},{"ANIO":2024,"TIPO_ACCIDENTE_NOMBRE":14.0,"TOTAL":3},{"ANIO":2024,"TIPO_ACCIDENTE_NOMBRE":15.0,"TOTAL":10},{"ANIO":2024,"TIPO_ACCIDENTE_NOMBRE":16.0,"TOTAL":64},{"ANIO":2024,"TIPO_ACCIDENTE_NOMBRE":17.0,"TOTAL":7},{"ANIO":2024,"TIPO_ACCIDENTE_NOMBRE":18.0,"TOTAL":5},{"ANIO":2024,"TIPO_ACCIDENTE_NOMBRE":19.0,"TOTAL":36},{"ANIO":2024,"TIPO_ACCIDENTE_NOMBRE":20.0,"TOTAL":12}]